fastapi_tools/ldap/__init__.py
fastapi_tools/ldap/client.py
fastapi_tools/ldap/config.py
fastapi_tools/ldap/py.typed
fastapi_tools_ldap-0.1.1.dist-info/METADATA
fastapi_tools_ldap-0.1.1.dist-info/WHEEL
fastapi_tools_ldap-0.1.1.dist-info/RECORD
