Metadata-Version: 2.3
Name: fastapi-tools-ldap
Version: 0.1.1
Summary: Fastapi ldap integration
Author: Andrei Churin
Author-email: aachurin@gmail.com
Requires-Python: >=3.12,<4.0
Classifier: Programming Language :: Python :: 3
Classifier: Programming Language :: Python :: 3.12
Classifier: Programming Language :: Python :: 3.13
Requires-Dist: bonsai (>=1.5.3,<2.0.0)
Requires-Dist: pydantic (>=2.10.5,<3.0.0)
